casymda/BPMN/BPMNParser.py
casymda/CoreBlocks/CoreComponent.py
casymda/CoreBlocks/CoreEntity.py
casymda/CoreBlocks/CoreGateway.py
casymda/CoreBlocks/CoreProcess.py
casymda/CoreBlocks/CoreReleaseRes.py
casymda/CoreBlocks/CoreResource.py
casymda/CoreBlocks/CoreSPR.py
casymda/CoreBlocks/CoreSeizeResourceQueue.py
casymda/CoreBlocks/CoreSink.py
casymda/CoreBlocks/CoreSource.py
casymda/CoreBlocks/CoreWaitForInterrupt.py
casymda/CoreBlocks/__init__.py
casymda/Visualization/ProcessVisualizer.py
casymda/Visualization/TkCanvas.py
casymda/Visualization/WebCanvas.py
casymda/Visualization/state_icons/blocked.png
casymda/Visualization/state_icons/busy.png
casymda/Visualization/state_icons/empty.png
casymda/WIP/WIP.py
casymda/version/__init__.py
casymda-0.1.9.dist-info/LICENSE
casymda-0.1.9.dist-info/METADATA
casymda-0.1.9.dist-info/WHEEL
casymda-0.1.9.dist-info/top_level.txt
casymda-0.1.9.dist-info/RECORD
